[
  {"code": "A1101", "libelle": "Conduite d'engins agricoles et forestiers"},
  {"code": "A1201", "libelle": "Bûcheronnage et élagage"},
  {"code": "A1202", "libelle": "Entretien des espaces naturels"},
  {"code": "A1203", "libelle": "Aménagement et entretien des espaces verts"},
  {"code": "A1204", "libelle": "Protection du patrimoine naturel"},
  {"code": "A1301", "libelle": "Conseil et assistance technique en agriculture et environnement naturel"},
  {"code": "A1302", "libelle": "Contrôle et diagnostic technique en agriculture"},
  {"code": "A1303", "libelle": "Ingénierie en agriculture et environnement naturel"},
  {"code": "A1401", "libelle": "Aide agricole de production légumière ou végétale"},
  {"code": "A1402", "libelle": "Aide agricole de production fruitière ou viticole"},
  {"code": "A1403", "libelle": "Aide d'élevage agricole et aquacole"},
  {"code": "A1404", "libelle": "Aquaculture"},
  {"code": "A1405", "libelle": "Arboriculture et viticulture"},
  {"code": "A1406", "libelle": "Encadrement équipage de la pêche"},
  {"code": "A1407", "libelle": "Élevage bovin ou équin"},
  {"code": "A1408", "libelle": "Élevage d'animaux sauvages ou de compagnie"},
  {"code": "A1409", "libelle": "Élevage de lapins et volailles"},
  {"code": "A1410", "libelle": "Élevage ovin ou caprin"},
  {"code": "A1411", "libelle": "Élevage porcin"},
  {"code": "A1412", "libelle": "Fabrication et affinage de fromages"},
  {"code": "A1413", "libelle": "Fermentation de boissons alcoolisées"},
  {"code": "A1414", "libelle": "Horticulture et maraîchage"},
  {"code": "A1415", "libelle": "Équipage de la pêche"},
  {"code": "A1416", "libelle": "Polyculture, élevage"},
  {"code": "B1101", "libelle": "Création en arts plastiques"},
  {"code": "B1201", "libelle": "Réalisation d'articles de joaillerie et bijouterie"},
  {"code": "B1301", "libelle": "Décoration d'espaces de vente et d'exposition"},
  {"code": "B1302", "libelle": "Décoration d'objets d'art et artisanaux"},
  {"code": "B1401", "libelle": "Gravure - ciselure"},
  {"code": "B1402", "libelle": "Reliure et restauration de livres et archives"},
  {"code": "B1501", "libelle": "Fabrication et façonnage d'éléments en verre"},
  {"code": "B1601", "libelle": "Métallerie d'art"},
  {"code": "B1701", "libelle": "Conservation et reconstitution d'espèces animales"},
  {"code": "B1801", "libelle": "Réalisation d'objets décoratifs et utilitaires en céramique et matériaux de synthèse"},
  {"code": "B1802", "libelle": "Réalisation d'objets en liège, vannerie et sparterie"},
  {"code": "B1803", "libelle": "Réalisation de motifs décoratifs et artistiques"},
  {"code": "D1101", "libelle": "Boucherie"},
  {"code": "D1102", "libelle": "Boulangerie - viennoiserie"},
  {"code": "D1103", "libelle": "Charcuterie - traiteur"},
  {"code": "D1104", "libelle": "Pâtisserie, confiserie, chocolaterie et glacerie"},
  {"code": "D1105", "libelle": "Poissonnerie"},
  {"code": "D1106", "libelle": "Vente en alimentation"},
  {"code": "D1107", "libelle": "Vente en gros de produits frais"},
  {"code": "D1201", "libelle": "Achat vente d'objets d'art, anciens ou d'occasion"},
  {"code": "D1202", "libelle": "Coiffure"},
  {"code": "D1203", "libelle": "Gérance de locaux d'habitation"},
  {"code": "D1204", "libelle": "Location de biens immobiliers"},
  {"code": "D1205", "libelle": "Vente de végétaux"},
  {"code": "D1206", "libelle": "Vente en décoration et équipement du foyer"},
  {"code": "D1207", "libelle": "Vente de livres"},
  {"code": "D1208", "libelle": "Vente d'articles de sport et de loisirs"},
  {"code": "D1209", "libelle": "Vente de végétaux"},
  {"code": "D1210", "libelle": "Vente en animalerie"},
  {"code": "D1211", "libelle": "Vente en articles de sport et loisirs"},
  {"code": "D1212", "libelle": "Vente en équipement du foyer"},
  {"code": "D1213", "libelle": "Vente en gros de matériel et équipement"},
  {"code": "D1214", "libelle": "Vente en habillement et accessoires de la personne"},
  {"code": "D1301", "libelle": "Management de magasin de détail"},
  {"code": "D1401", "libelle": "Assistanat commercial"},
  {"code": "D1402", "libelle": "Relation commerciale grands comptes et entreprises"},
  {"code": "D1403", "libelle": "Relation commerciale auprès de particuliers"},
  {"code": "D1404", "libelle": "Relation commerciale en vente de véhicules"},
  {"code": "D1405", "libelle": "Conseil en information médicale"},
  {"code": "D1406", "libelle": "Management en force de vente"},
  {"code": "D1407", "libelle": "Relation technico-commerciale"},
  {"code": "D1408", "libelle": "Téléconseil et télévente"},
  {"code": "D1501", "libelle": "Animation de vente"},
  {"code": "D1502", "libelle": "Management/gestion de rayon produits alimentaires"},
  {"code": "D1503", "libelle": "Management/gestion de rayon produits non alimentaires"},
  {"code": "D1504", "libelle": "Mise en rayon libre-service"},
  {"code": "D1505", "libelle": "Personnel de caisse"},
  {"code": "D1506", "libelle": "Marchandisage"},
  {"code": "D1507", "libelle": "Mise en rayon libre-service"},
  {"code": "D1508", "libelle": "Tenue de caisse"},
  {"code": "E1101", "libelle": "Animation de site multimédia"},
  {"code": "E1102", "libelle": "Écriture d'ouvrages, de livres"},
  {"code": "E1103", "libelle": "Communication"},
  {"code": "E1104", "libelle": "Conception de contenus multimédias"},
  {"code": "E1105", "libelle": "Coordination d'édition"},
  {"code": "E1106", "libelle": "Journalisme et information média"},
  {"code": "E1107", "libelle": "Organisation d'événementiel"},
  {"code": "E1108", "libelle": "Traduction, interprétariat"},
  {"code": "E1201", "libelle": "Photographie"},
  {"code": "E1202", "libelle": "Prise de vues et retouche en laboratoire photographique"},
  {"code": "E1203", "libelle": "Production en laboratoire cinématographique"},
  {"code": "E1204", "libelle": "Projection cinéma"},
  {"code": "E1205", "libelle": "Réalisation de contenus multimédias"},
  {"code": "E1301", "libelle": "Conduite de ligne de conditionnement"},
  {"code": "E1302", "libelle": "Graphisme en industrie graphique"},
  {"code": "E1303", "libelle": "Gravure - ciselure"},
  {"code": "E1304", "libelle": "Intervention technique en méthodes et industrialisation"},
  {"code": "E1305", "libelle": "Préparation et correction en prépresse"},
  {"code": "E1306", "libelle": "Prépresse"},
  {"code": "F1101", "libelle": "Architecture du BTP"},
  {"code": "F1102", "libelle": "Conception - aménagement d'espaces intérieurs"},
  {"code": "F1103", "libelle": "Contrôle et diagnostic technique du bâtiment"},
  {"code": "F1104", "libelle": "Dessin BTP et paysage"},
  {"code": "F1105", "libelle": "Études géologiques"},
  {"code": "F1106", "libelle": "Ingénierie et études du BTP"},
  {"code": "F1201", "libelle": "Conduite de travaux du BTP"},
  {"code": "F1202", "libelle": "Direction de chantier du BTP"},
  {"code": "F1203", "libelle": "Direction et ingénierie d'exploitation de gisements et de carrières"},
  {"code": "F1204", "libelle": "Sécurité et surveillance privées"},
  {"code": "F1301", "libelle": "Conduite de grue"},
  {"code": "F1302", "libelle": "Conduite d'engins de terrassement et de carrière"},
  {"code": "F1401", "libelle": "Extraction"},
  {"code": "F1402", "libelle": "Extraction liquide et gazeuse"},
  {"code": "F1501", "libelle": "Montage de structures et de charpentes bois"},
  {"code": "F1502", "libelle": "Montage de structures métalliques"},
  {"code": "F1503", "libelle": "Réalisation - installation d'ossatures bois"},
  {"code": "F1601", "libelle": "Application et décoration en plâtre, stuc et staff"},
  {"code": "F1602", "libelle": "Électricité bâtiment"},
  {"code": "F1603", "libelle": "Installation d'équipements sanitaires et thermiques"},
  {"code": "F1604", "libelle": "Montage d'agencements"},
  {"code": "F1605", "libelle": "Montage de réseaux électriques et télécoms"},
  {"code": "F1606", "libelle": "Peinture en bâtiment"},
  {"code": "F1607", "libelle": "Pose de fermetures menuisées"},
  {"code": "F1608", "libelle": "Pose de revêtements rigides"},
  {"code": "F1609", "libelle": "Pose et restauration de couvertures"},
  {"code": "F1610", "libelle": "Pose et restauration de menuiseries"},
  {"code": "F1611", "libelle": "Réalisation et restauration de façades"},
  {"code": "F1612", "libelle": "Taille et décoration de pierres"},
  {"code": "F1613", "libelle": "Travaux d'étanchéité et d'isolation"},
  {"code": "F1701", "libelle": "Construction en béton"},
  {"code": "F1702", "libelle": "Construction de routes et voies"},
  {"code": "F1703", "libelle": "Maçonnerie"},
  {"code": "F1704", "libelle": "Préparation du gros oeuvre et des travaux publics"},
  {"code": "G1101", "libelle": "Accueil touristique"},
  {"code": "G1102", "libelle": "Promotion du tourisme local"},
  {"code": "G1201", "libelle": "Accompagnement de voyages, d'activités culturelles ou sportives"},
  {"code": "G1202", "libelle": "Animation d'activités culturelles ou ludiques"},
  {"code": "G1203", "libelle": "Animation de loisirs auprès d'enfants ou d'adolescents"},
  {"code": "G1204", "libelle": "Éducation en activités sportives"},
  {"code": "G1205", "libelle": "Personnel d'attractions ou de structures de loisirs"},
  {"code": "G1301", "libelle": "Conception de produits touristiques"},
  {"code": "G1302", "libelle": "Gestion d'hôtellerie"},
  {"code": "G1303", "libelle": "Gestion de structure de loisirs ou d'hébergement touristique"},
  {"code": "G1401", "libelle": "Assistance de direction d'hôtel-restaurant"},
  {"code": "G1402", "libelle": "Management d'hôtel-restaurant"},
  {"code": "G1403", "libelle": "Gestion de structure de loisirs ou d'hébergement touristique"},
  {"code": "G1404", "libelle": "Management d'établissement de restauration collective"},
  {"code": "G1501", "libelle": "Personnel d'étage"},
  {"code": "G1502", "libelle": "Personnel polyvalent d'hôtellerie"},
  {"code": "G1503", "libelle": "Management du personnel de cuisine"},
  {"code": "G1601", "libelle": "Management du personnel de salle"},
  {"code": "G1602", "libelle": "Personnel de cuisine"},
  {"code": "G1603", "libelle": "Personnel polyvalent en restauration"},
  {"code": "G1701", "libelle": "Blanchisserie - Pressing"},
  {"code": "G1702", "libelle": "Entretien et propreté de locaux"},
  {"code": "G1703", "libelle": "Personnel d'entretien de nettoyage"},
  {"code": "G1801", "libelle": "Café, bar brasserie"},
  {"code": "G1802", "libelle": "Management du service en restauration"},
  {"code": "G1803", "libelle": "Service en restauration"},
  {"code": "H1101", "libelle": "Assistance et support technique client"},
  {"code": "H1102", "libelle": "Management et ingénierie d'affaires"},
  {"code": "H1201", "libelle": "Expertise environnementale BTP"},
  {"code": "H1202", "libelle": "Conception et dessin de produits électriques et électroniques"},
  {"code": "H1203", "libelle": "Conception et dessin de produits mécaniques"},
  {"code": "H1204", "libelle": "Design industriel"},
  {"code": "H1205", "libelle": "Études - modèles en industrie des matériaux souples"},
  {"code": "H1206", "libelle": "Management et ingénierie études, recherche et développement industriel"},
  {"code": "H1207", "libelle": "Rédaction technique"},
  {"code": "H1208", "libelle": "Intervention technique en études et conception en automatisme"},
  {"code": "H1209", "libelle": "Intervention technique en études et développement électronique"},
  {"code": "H1210", "libelle": "Intervention technique en études, recherche et développement"},
  {"code": "H1301", "libelle": "Inspection de conformité"},
  {"code": "H1302", "libelle": "Management et ingénierie Hygiène Sécurité Environnement -HSE- industriels"},
  {"code": "H1303", "libelle": "Intervention technique en Hygiène Sécurité Environnement -HSE- industriel"},
  {"code": "H1401", "libelle": "Management et ingénierie gestion industrielle et logistique"},
  {"code": "H1402", "libelle": "Management et ingénierie méthodes et industrialisation"},
  {"code": "H1403", "libelle": "Intervention technique en gestion industrielle et logistique"},
  {"code": "H1404", "libelle": "Intervention technique en méthodes et industrialisation"},
  {"code": "H1501", "libelle": "Direction de laboratoire d'analyse industrielle"},
  {"code": "H1502", "libelle": "Management et ingénierie qualité industrielle"},
  {"code": "H1503", "libelle": "Intervention technique en laboratoire d'analyse industrielle"},
  {"code": "H1504", "libelle": "Intervention technique en contrôle essai qualité en électricité et électronique"},
  {"code": "H1505", "libelle": "Intervention technique en formulation et analyse sensorielle"},
  {"code": "H1506", "libelle": "Intervention technique qualité en mécanique et travail des métaux"},
  {"code": "H1507", "libelle": "Intervention technique en études et développement"},
  {"code": "H2101", "libelle": "Abattage et découpe des viandes"},
  {"code": "H2102", "libelle": "Conduite d'équipement de production alimentaire"},
  {"code": "H2201", "libelle": "Assemblage d'ouvrages en bois"},
  {"code": "H2202", "libelle": "Conduite d'équipement de fabrication de l'ameublement et du bois"},
  {"code": "H2203", "libelle": "Conduite d'installation de pâte à papier ou de papier carton"},
  {"code": "H2204", "libelle": "Encadrement des industries de l'ameublement et du bois"},
  {"code": "H2205", "libelle": "Première transformation de bois d'oeuvre"},
  {"code": "H2206", "libelle": "Réalisation de menuiserie bois et PVC"},
  {"code": "H2207", "libelle": "Réalisation de meubles en bois"},
  {"code": "H2208", "libelle": "Réalisation d'ouvrages décoratifs en bois"},
  {"code": "H2209", "libelle": "Intervention technique en ameublement et bois"},
  {"code": "H2301", "libelle": "Conduite d'équipement de fabrication de papier ou de carton"},
  {"code": "H2401", "libelle": "Assemblage - montage d'articles en cuirs, peaux"},
  {"code": "H2402", "libelle": "Assemblage - montage de vêtements et produits textiles"},
  {"code": "H2403", "libelle": "Conduite de machine de fabrication de produits textiles"},
  {"code": "H2404", "libelle": "Conduite de machine de traitement textile"},
  {"code": "H2405", "libelle": "Conduite de machine de production et transformation des fils"},
  {"code": "H2406", "libelle": "Conduite de machine de texturation et de transformation des fils"},
  {"code": "H2407", "libelle": "Conduite de machine de transformation et de finition des cuirs et peaux"},
  {"code": "H2408", "libelle": "Conduite de machine de teinture et d'apprêt des textiles"},
  {"code": "H2409", "libelle": "Coupe cuir, textile et matériaux souples"},
  {"code": "H2410", "libelle": "Mise en forme, repassage, finition en industrie textile"},
  {"code": "H2411", "libelle": "Montage en ameublement, agencement, structures métalliques"},
  {"code": "H2412", "libelle": "Patronnage - gradation"},
  {"code": "H2413", "libelle": "Préparation de matières et produits en industrie textile"},
  {"code": "H2414", "libelle": "Préparation et finition d'articles en cuir et matériaux souples"},
  {"code": "H2415", "libelle": "Contrôle en industrie du cuir et du textile"},
  {"code": "H2501", "libelle": "Encadrement de production de matériel électrique et électronique"},
  {"code": "H2502", "libelle": "Management et ingénierie de production"},
  {"code": "H2503", "libelle": "Pilotage d'unité élémentaire de production mécanique ou de travail des métaux"},
  {"code": "H2504", "libelle": "Encadrement d'équipe en industrie de transformation"},
  {"code": "H2601", "libelle": "Bobinage électrique"},
  {"code": "H2602", "libelle": "Câblage électrique et électromécanique"},
  {"code": "H2603", "libelle": "Conduite d'installation automatisée de production électrique, électronique et microélectronique"},
  {"code": "H2604", "libelle": "Montage de produits électriques et électroniques"},
  {"code": "H2605", "libelle": "Montage et câblage électronique"},
  {"code": "H2701", "libelle": "Pilotage d'installation énergétique et pétrochimique"},
  {"code": "H2801", "libelle": "Conduite d'installation de production de bétons"},
  {"code": "H2802", "libelle": "Conduite d'installation de production de matériaux de construction"},
  {"code": "H2803", "libelle": "Façonnage et émaillage en industrie céramique"},
  {"code": "H2804", "libelle": "Pilotage de centrale à béton prêt à l'emploi, ciment, enrobés et granulats"},
  {"code": "H2805", "libelle": "Pilotage d'installation de production verrière"},
  {"code": "H2806", "libelle": "Pilotage d'installation de traitement et de conditionnement"},
  {"code": "H2901", "libelle": "Ajustement et montage de fabrication"},
  {"code": "H2902", "libelle": "Chaudronnerie - tôlerie"},
  {"code": "H2903", "libelle": "Conduite d'équipement d'usinage"},
  {"code": "H2904", "libelle": "Conduite d'équipement de déformation des métaux"},
  {"code": "H2905", "libelle": "Conduite d'équipement de formage et découpage des matériaux"},
  {"code": "H2906", "libelle": "Conduite d'installation automatisée ou robotisée de fabrication mécanique"},
  {"code": "H2907", "libelle": "Conduite d'installation de production des métaux"},
  {"code": "H2908", "libelle": "Modelage de matériaux non métalliques"},
  {"code": "H2909", "libelle": "Montage-assemblage mécanique"},
  {"code": "H2910", "libelle": "Moulage sable"},
  {"code": "H2911", "libelle": "Réalisation de structures métalliques"},
  {"code": "H2912", "libelle": "Réglage d'équipement de formage des plastiques et caoutchoucs"},
  {"code": "H2913", "libelle": "Soudage manuel"},
  {"code": "H2914", "libelle": "Réalisation et montage en tuyauterie"},
  {"code": "H3101", "libelle": "Conduite d'équipement de transformation du verre"},
  {"code": "H3201", "libelle": "Conduite d'équipement de production chimique ou pharmaceutique"},
  {"code": "H3202", "libelle": "Réglage d'équipement de fabrication industrielle"},
  {"code": "H3203", "libelle": "Fabrication de pâte à papier et de papier"},
  {"code": "H3301", "libelle": "Conduite d'équipement de fabrication de produits pharmaceutiques"},
  {"code": "H3302", "libelle": "Opérations manuelles d'assemblage, tri ou emballage"},
  {"code": "H3303", "libelle": "Préparation de matières et produits industriels (broyage, mélange, ...)"},
  {"code": "H3401", "libelle": "Conduite de traitement d'abrasion de surface"},
  {"code": "H3402", "libelle": "Conduite de traitement par dépôt de surface"},
  {"code": "H3403", "libelle": "Conduite de traitement thermique"},
  {"code": "H3404", "libelle": "Peinture industrielle"},
  {"code": "I1101", "libelle": "Direction et ingénierie en entretien infrastructure et bâti"},
  {"code": "I1102", "libelle": "Management et ingénierie de maintenance industrielle"},
  {"code": "I1201", "libelle": "Entretien et surveillance du bâti"},
  {"code": "I1202", "libelle": "Entretien et surveillance du matériel"},
  {"code": "I1203", "libelle": "Maintenance des bâtiments et des locaux"},
  {"code": "I1301", "libelle": "Installation et maintenance d'ascenseurs"},
  {"code": "I1302", "libelle": "Installation et maintenance d'automatismes"},
  {"code": "I1303", "libelle": "Installation et maintenance de distributeurs automatiques"},
  {"code": "I1304", "libelle": "Installation et maintenance d'équipements industriels et d'exploitation"},
  {"code": "I1305", "libelle": "Installation et maintenance électronique"},
  {"code": "I1306", "libelle": "Installation et maintenance en froid, conditionnement d'air"},
  {"code": "I1307", "libelle": "Installation et maintenance télécoms et courants faibles"},
  {"code": "I1308", "libelle": "Maintenance d'installation de chauffage"},
  {"code": "I1309", "libelle": "Maintenance électrique"},
  {"code": "I1310", "libelle": "Maintenance mécanique industrielle"},
  {"code": "I1401", "libelle": "Maintenance informatique et bureautique"},
  {"code": "I1402", "libelle": "Réparation de biens électrodomestiques"},
  {"code": "I1501", "libelle": "Intervention en milieu subaquatique"},
  {"code": "I1502", "libelle": "Intervention en grande hauteur"},
  {"code": "I1503", "libelle": "Intervention en milieux et produits nocifs"},
  {"code": "I1601", "libelle": "Entretien et réparation d'avion"},
  {"code": "I1602", "libelle": "Maintenance d'aéronefs"},
  {"code": "I1603", "libelle": "Maintenance d'engins de chantier, levage, manutention et de machines agricoles"},
  {"code": "I1604", "libelle": "Mécanique automobile et entretien de véhicules"},
  {"code": "I1605", "libelle": "Mécanique de marine"},
  {"code": "I1606", "libelle": "Réparation de carrosserie"},
  {"code": "I1607", "libelle": "Réparation de cycles, motocycles et motoculteurs de loisirs"},
  {"code": "J1101", "libelle": "Médecine de prévention"},
  {"code": "J1102", "libelle": "Médecine généraliste et spécialisée"},
  {"code": "J1103", "libelle": "Médecine dentaire"},
  {"code": "J1104", "libelle": "Pharmacie"},
  {"code": "J1105", "libelle": "Médecine vétérinaire"},
  {"code": "J1201", "libelle": "Biologie médicale et pharmacie hospitalière"},
  {"code": "J1301", "libelle": "Personnel polyvalent des services hospitaliers"},
  {"code": "J1302", "libelle": "Assistance médicale à la procréation"},
  {"code": "J1303", "libelle": "Intervention d'urgence sociale et familiale"},
  {"code": "J1304", "libelle": "Aide en puériculture"},
  {"code": "J1305", "libelle": "Conduite de véhicules sanitaires"},
  {"code": "J1401", "libelle": "Audioprothèses"},
  {"code": "J1402", "libelle": "Instrumentation et équipement industriel"},
  {"code": "J1403", "libelle": "Intervention de support en milieu de soins"},
  {"code": "J1404", "libelle": "Manipulation d'analyses médicales"},
  {"code": "J1405", "libelle": "Optique - lunetterie"},
  {"code": "J1406", "libelle": "Prothèses dentaires"},
  {"code": "J1407", "libelle": "Prothèses et orthèses"},
  {"code": "J1501", "libelle": "Soins d'hygiène, de confort du patient"},
  {"code": "J1502", "libelle": "Coordination de services médicaux ou paramédicaux"},
  {"code": "J1503", "libelle": "Ergothérapie"},
  {"code": "J1504", "libelle": "Kinésithérapie"},
  {"code": "J1505", "libelle": "Soins infirmiers spécialisés en anesthésie"},
  {"code": "J1506", "libelle": "Soins infirmiers généralistes"},
  {"code": "J1507", "libelle": "Soins infirmiers spécialisés en bloc opératoire"},
  {"code": "J1508", "libelle": "Soins infirmiers spécialisés en prévention"},
  {"code": "J1509", "libelle": "Soins infirmiers spécialisés en puériculture"},
  {"code": "J1510", "libelle": "Soins et activités sur les lieux de vie"},
  {"code": "J1511", "libelle": "Soins et activités sur les lieux de vie en établissement de santé"},
  {"code": "K1101", "libelle": "Accompagnement et médiation familiale"},
  {"code": "K1201", "libelle": "Action sociale"},
  {"code": "K1202", "libelle": "Éducation de jeunes enfants"},
  {"code": "K1203", "libelle": "Encadrement technique en insertion professionnelle"},
  {"code": "K1204", "libelle": "Médiation sociale et facilitation de la vie en société"},
  {"code": "K1205", "libelle": "Information sociale"},
  {"code": "K1206", "libelle": "Intervention socioculturelle"},
  {"code": "K1207", "libelle": "Intervention socioéducative"},
  {"code": "K1301", "libelle": "Accompagnement médicosocial"},
  {"code": "K1302", "libelle": "Assistance auprès d'adultes"},
  {"code": "K1303", "libelle": "Assistance auprès d'enfants"},
  {"code": "K1304", "libelle": "Services domestiques"},
  {"code": "K1305", "libelle": "Intervention sociale et familiale"},
  {"code": "K1401", "libelle": "Conception et pilotage de la politique des pouvoirs publics"},
  {"code": "K1402", "libelle": "Conseil en Santé Publique"},
  {"code": "K1403", "libelle": "Management de structure de santé, sociale ou pénitentiaire"},
  {"code": "K1404", "libelle": "Mise en oeuvre et pilotage de la politique des pouvoirs publics"},
  {"code": "K1501", "libelle": "Accompagnement de spectacles, administration de la culture"},
  {"code": "K1601", "libelle": "Gestion de l'information et de la documentation"},
  {"code": "K1602", "libelle": "Gestion de patrimoine culturel"},
  {"code": "K1701", "libelle": "Personnel de bibliothèque et de documentation"},
  {"code": "K1702", "libelle": "Personnel des musées et des sites"},
  {"code": "K1801", "libelle": "Conseil en emploi et insertion socioprofessionnelle"},
  {"code": "K1802", "libelle": "Développement local"},
  {"code": "K1901", "libelle": "Aide et médiation judiciaire"},
  {"code": "K2101", "libelle": "Conseil en formation"},
  {"code": "K2102", "libelle": "Coordination pédagogique"},
  {"code": "K2103", "libelle": "Direction d'établissement et d'enseignement"},
  {"code": "K2104", "libelle": "Éducation et surveillance au sein d'établissements d'enseignement"},
  {"code": "K2105", "libelle": "Enseignement artistique"},
  {"code": "K2106", "libelle": "Enseignement des écoles"},
  {"code": "K2107", "libelle": "Enseignement général du second degré"},
  {"code": "K2108", "libelle": "Enseignement supérieur"},
  {"code": "K2109", "libelle": "Enseignement technique et professionnel"},
  {"code": "K2110", "libelle": "Formation en conduite de véhicules"},
  {"code": "K2111", "libelle": "Formation professionnelle"},
  {"code": "K2112", "libelle": "Orientation scolaire et professionnelle"},
  {"code": "K2201", "libelle": "Recherche en sciences de l'homme et de la société"},
  {"code": "K2202", "libelle": "Recherche en sciences de l'univers, de la matière et du vivant"},
  {"code": "K2301", "libelle": "Enseignement de formateurs"},
  {"code": "K2401", "libelle": "Recherche en sciences de l'homme et de la société"},
  {"code": "L1101", "libelle": "Animation musicale et scénique"},
  {"code": "L1102", "libelle": "Enseignement artistique"},
  {"code": "L1201", "libelle": "Régie générale"},
  {"code": "L1202", "libelle": "Musique et chant"},
  {"code": "L1203", "libelle": "Conception de spectacles et mise en scène"},
  {"code": "L1204", "libelle": "Éclairage spectacles"},
  {"code": "L1205", "libelle": "Réalisation de contenus multimédias"},
  {"code": "L1301", "libelle": "Administration de spectacles"},
  {"code": "L1302", "libelle": "Production et administration spectacle, cinéma et audiovisuel"},
  {"code": "L1303", "libelle": "Promotion d'artistes et de spectacles"},
  {"code": "L1304", "libelle": "Régie générale"},
  {"code": "L1401", "libelle": "Circonstances et personnages de théâtre"},
  {"code": "L1501", "libelle": "Danse"},
  {"code": "L1502", "libelle": "Artiste de cirque"},
  {"code": "L1503", "libelle": "Décor et accessoires spectacles"},
  {"code": "L1504", "libelle": "Éclairage spectacles"},
  {"code": "L1505", "libelle": "Image cinématographique et télévisuelle"},
  {"code": "L1506", "libelle": "Machinerie spectacle"},
  {"code": "L1507", "libelle": "Montage et post-production"},
  {"code": "L1508", "libelle": "Prise de son et sonorisation"},
  {"code": "M1101", "libelle": "Achats"},
  {"code": "M1102", "libelle": "Direction des achats"},
  {"code": "M1201", "libelle": "Analyse et ingénierie financière"},
  {"code": "M1202", "libelle": "Audit et contrôle comptables et financiers"},
  {"code": "M1203", "libelle": "Comptabilité"},
  {"code": "M1204", "libelle": "Contrôle de gestion"},
  {"code": "M1205", "libelle": "Direction administrative et financière"},
  {"code": "M1206", "libelle": "Management de groupe ou de service comptable"},
  {"code": "M1207", "libelle": "Trésorerie et financement"},
  {"code": "M1301", "libelle": "Direction de grande entreprise ou d'établissement public"},
  {"code": "M1302", "libelle": "Direction de petite ou moyenne entreprise"},
  {"code": "M1401", "libelle": "Assistanat de direction"},
  {"code": "M1402", "libelle": "Conseil en organisation et management d'entreprise"},
  {"code": "M1403", "libelle": "Études et prospectives socio-économiques"},
  {"code": "M1501", "libelle": "Assistanat en ressources humaines"},
  {"code": "M1502", "libelle": "Développement des ressources humaines"},
  {"code": "M1503", "libelle": "Management des ressources humaines"},
  {"code": "M1601", "libelle": "Accueil et renseignements"},
  {"code": "M1602", "libelle": "Opérations administratives"},
  {"code": "M1603", "libelle": "Secrétariat médical et médico-social"},
  {"code": "M1604", "libelle": "Assistanat de gestion administrative"},
  {"code": "M1605", "libelle": "Assistanat technique et administratif"},
  {"code": "M1606", "libelle": "Saisie de données"},
  {"code": "M1607", "libelle": "Secrétariat"},
  {"code": "M1608", "libelle": "Secrétariat comptable"},
  {"code": "M1701", "libelle": "Administration des ventes"},
  {"code": "M1702", "libelle": "Analyse de tendances"},
  {"code": "M1703", "libelle": "Management et gestion de produit"},
  {"code": "M1704", "libelle": "Management relation clientèle"},
  {"code": "M1705", "libelle": "Marketing"},
  {"code": "M1706", "libelle": "Promotion des ventes"},
  {"code": "M1707", "libelle": "Stratégie commerciale"},
  {"code": "M1801", "libelle": "Administration de systèmes d'information"},
  {"code": "M1802", "libelle": "Expertise et support en systèmes d'information"},
  {"code": "M1803", "libelle": "Direction des systèmes d'information"},
  {"code": "M1804", "libelle": "Études et développement de réseaux de télécoms"},
  {"code": "M1805", "libelle": "Études et développement informatique"},
  {"code": "M1806", "libelle": "Conseil et maîtrise d'ouvrage en systèmes d'information"},
  {"code": "M1807", "libelle": "Exploitation de systèmes de communication et de commandement"},
  {"code": "M1808", "libelle": "Information géographique"},
  {"code": "M1809", "libelle": "Information météorologique"},
  {"code": "M1810", "libelle": "Production et exploitation de systèmes d'information"},
  {"code": "N1101", "libelle": "Conduite d'engins de déplacement des charges"},
  {"code": "N1102", "libelle": "Déménagement"},
  {"code": "N1103", "libelle": "Magasinage et préparation de commandes"},
  {"code": "N1104", "libelle": "Manoeuvre et conduite d'engins lourds de manutention"},
  {"code": "N1105", "libelle": "Manutention manuelle de charges"},
  {"code": "N1201", "libelle": "Affrètement transport"},
  {"code": "N1202", "libelle": "Gestion des opérations de circulation internationale des marchandises"},
  {"code": "N1301", "libelle": "Conception et organisation de la chaîne logistique"},
  {"code": "N1302", "libelle": "Direction de site logistique"},
  {"code": "N1303", "libelle": "Intervention technique d'exploitation logistique"},
  {"code": "N2101", "libelle": "Navigation commerciale aérienne"},
  {"code": "N2102", "libelle": "Pilotage et navigation technique aérienne"},
  {"code": "N2201", "libelle": "Personnel d'escale aéroportuaire"},
  {"code": "N2202", "libelle": "Contrôle aérien"},
  {"code": "N2203", "libelle": "Exploitation du transport aérien"},
  {"code": "N2204", "libelle": "Préparation des vols"},
  {"code": "N3101", "libelle": "Encadrement de la navigation maritime"},
  {"code": "N3102", "libelle": "Équipage de la navigation maritime"},
  {"code": "N3103", "libelle": "Navigation fluviale"},
  {"code": "N3201", "libelle": "Exploitation du transport maritime et fluvial"},
  {"code": "N3301", "libelle": "Conception et organisation de la circulation ferroviaire"},
  {"code": "N4101", "libelle": "Conduite de transport de marchandises sur longue distance"},
  {"code": "N4102", "libelle": "Conduite de transport de particuliers"},
  {"code": "N4103", "libelle": "Conduite de transport en commun sur route"},
  {"code": "N4104", "libelle": "Courses et livraisons express"},
  {"code": "N4105", "libelle": "Conduite et livraison par tournées sur courte distance"},
  {"code": "N4201", "libelle": "Direction d'exploitation des transports routiers de personnes"},
  {"code": "N4202", "libelle": "Direction d'exploitation des transports routiers de marchandises"},
  {"code": "N4203", "libelle": "Intervention technique d'exploitation des transports routiers de marchandises"},
  {"code": "N4301", "libelle": "Conduite sur rails"},
  {"code": "N4302", "libelle": "Contrôle et surveillance du trafic de transport ferroviaire"},
  {"code": "N4401", "libelle": "Circulation du réseau ferré"},
  {"code": "N4402", "libelle": "Exploitation et manoeuvre des remontées mécaniques"},
  {"code": "N4403", "libelle": "Manoeuvre du réseau ferré"},
  {"code": "Q1101", "libelle": "Désamiantage"},
  {"code": "Q1201", "libelle": "Dépollution"},
  {"code": "Q1301", "libelle": "Accompagnement de projets de développement local"},
  {"code": "Q1302", "libelle": "Accompagnement de voyages, d'activités culturelles ou sportives"},
  {"code": "Q1303", "libelle": "Assistance technique de la forêt"},
  {"code": "Q1401", "libelle": "Extraction"},
  {"code": "K1207", "libelle": "Intervention socioéducative"}
]
